flask_digest/__init__.py
flask_digest/challenge.py
flask_digest/hasher.py
flask_digest/maid.py
flask_digest/stomach.py
Flask_Digest-0.3.0.dist-info/LICENSE.txt
Flask_Digest-0.3.0.dist-info/METADATA
Flask_Digest-0.3.0.dist-info/WHEEL
Flask_Digest-0.3.0.dist-info/top_level.txt
Flask_Digest-0.3.0.dist-info/RECORD
