Metadata-Version: 2.1
Name: Flask-Digest
Version: 0.3.0
Summary: A RESTful authentication service for Flask applications
Home-page: https://github.com/vctandrade/flask-digest
Author: Victor Andrade de Almeida
Author-email: vct.a.almeida@gmail.com
License: MIT
Keywords: digest,authentication,flask
Platform: Platform Independent
Classifier: Development Status :: 3 - Alpha
Classifier: Environment :: Web Environment
Classifier: Framework :: Flask
Classifier: Intended Audience :: Developers
Classifier: License :: OSI Approved :: MIT License
Classifier: Natural Language :: English
Classifier: Operating System :: OS Independent
Classifier: Programming Language :: Python :: 3.10
Classifier: Programming Language :: Python :: Implementation
License-File: LICENSE.txt
Requires-Dist: Flask (>=2.2.2)
